dash_before_after/BeforeAfter.py
dash_before_after/__init__.py
dash_before_after/_imports_.py
dash_before_after/dash_before_after.min.js
dash_before_after/dash_before_after.min.js.map
dash_before_after/metadata.json
dash_before_after/package-info.json
dash_before_after-0.0.1.dist-info/LICENSE
dash_before_after-0.0.1.dist-info/METADATA
dash_before_after-0.0.1.dist-info/WHEEL
dash_before_after-0.0.1.dist-info/top_level.txt
dash_before_after-0.0.1.dist-info/RECORD
