Metadata-Version: 2.1
Name: dash-before-after
Version: 0.0.1
Summary: Project Description
Home-page: UNKNOWN
Author: Ann Marie Ward <amward@fastmail.com>
Author-email: UNKNOWN
License: MIT
Platform: UNKNOWN
Classifier: Framework :: Dash
